{
  "initial_balance": 100000.0,
  "final_balance": 100410.57987906496,
  "total_signals_generated": 36,
  "total_signals_executed": 13,
  "rejected_concurrency_lock": 2,
  "rejected_symbol_open_lock": 0,
  "rejected_symbol_cooldown_lock": 0,
  "rejected_low_priority": 0,
  "rejected_locks": 2,
  "rejected_other": 0,
  "rejected_signals": 23,
  "duplicate_signal_rejection_rate": 0.6388888888888888,
  "avg_executed_score": 0.4181885146885315,
  "avg_rejected_score": 0.38781665951779587,
  "avg_all_signal_score": 0.398784273885006,
  "selection_quality_ratio": 1.048658490502865,
  "ml_filtered_trades": 21,
  "ml_candidates_scored": 34,
  "avg_ml_score_executed": 0.5796347803023691,
  "avg_ml_score_rejected": 0.4737589752450958,
  "ml_acceptance_rate": 0.38235294117647056,
  "ml_fallback_count": 0,
  "ml_inference_error_count": 0,
  "acceptance_by_regime": {
    "TRENDING_LOW_VOL": {
      "candidates_scored": 28,
      "accepted": 10,
      "acceptance_rate": 0.35714285714285715
    },
    "RANGING_LOW_VOL": {
      "candidates_scored": 6,
      "accepted": 3,
      "acceptance_rate": 0.5
    }
  },
  "avg_threshold_modifier": 0.027941176470588233,
  "ml_score_distribution": {
    "min": 0.35068873731886374,
    "max": 0.66291822405029,
    "mean": 0.514240900708171,
    "std": 0.06748341697335707
  },
  "win_rate": 53.84615384615385,
  "profit_factor": 1.140901203723891,
  "net_pnl_pct": 0.41057987906497684,
  "max_drawdown_pct": -1.559628949949219,
  "cluster_event_count": 5,
  "cluster_event_total_size": 16,
  "cluster_event_avg_size": 3.2,
  "same_candle_multi_symbol_activations": 16,
  "co_activation_pairs": {
    "BTCUSDT|SUIUSDT": 2,
    "ARBUSDT|LDOUSDT": 1,
    "BTCUSDT|DOGEUSDT": 1,
    "SOLUSDT|TIAUSDT": 1,
    "APTUSDT|BTCUSDT": 1,
    "APTUSDT|FETUSDT": 1,
    "APTUSDT|LDOUSDT": 1,
    "APTUSDT|RUNEUSDT": 1,
    "APTUSDT|STXUSDT": 1,
    "APTUSDT|SUIUSDT": 1,
    "APTUSDT|WIFUSDT": 1,
    "BTCUSDT|FETUSDT": 1,
    "BTCUSDT|LDOUSDT": 1,
    "BTCUSDT|RUNEUSDT": 1,
    "BTCUSDT|STXUSDT": 1,
    "BTCUSDT|WIFUSDT": 1,
    "FETUSDT|LDOUSDT": 1,
    "FETUSDT|RUNEUSDT": 1,
    "FETUSDT|STXUSDT": 1,
    "FETUSDT|SUIUSDT": 1,
    "FETUSDT|WIFUSDT": 1,
    "LDOUSDT|RUNEUSDT": 1,
    "LDOUSDT|STXUSDT": 1,
    "LDOUSDT|SUIUSDT": 1,
    "LDOUSDT|WIFUSDT": 1,
    "RUNEUSDT|STXUSDT": 1,
    "RUNEUSDT|SUIUSDT": 1,
    "RUNEUSDT|WIFUSDT": 1,
    "STXUSDT|SUIUSDT": 1,
    "STXUSDT|WIFUSDT": 1,
    "SUIUSDT|WIFUSDT": 1
  }
}